MANIFEST.in
README.rst
README.txt
setup.cfg
setup.py
docs/CREDITS.txt
docs/HISTORY.txt
docs/INSTALL.txt
docs/LICENSE.GPL
docs/LICENSE.txt
src/collective/__init__.py
src/collective.iptvusp.egg-info/PKG-INFO
src/collective.iptvusp.egg-info/SOURCES.txt
src/collective.iptvusp.egg-info/dependency_links.txt
src/collective.iptvusp.egg-info/entry_points.txt
src/collective.iptvusp.egg-info/namespace_packages.txt
src/collective.iptvusp.egg-info/not-zip-safe
src/collective.iptvusp.egg-info/requires.txt
src/collective.iptvusp.egg-info/top_level.txt
src/collective/iptvusp/__init__.py
src/collective/iptvusp/config.py
src/collective/iptvusp/configure.zcml
src/collective/iptvusp/content.py
src/collective/iptvusp/controlpanel.py
src/collective/iptvusp/event.py
src/collective/iptvusp/interfaces.py
src/collective/iptvusp/profiles.zcml
src/collective/iptvusp/testing.py
src/collective/iptvusp/Extensions/Install.py
src/collective/iptvusp/Extensions/__init__.py
src/collective/iptvusp/locales/collective.cover.pot
src/collective/iptvusp/locales/collective.iptvusp.pot
src/collective/iptvusp/locales/manual.pot
src/collective/iptvusp/locales/plone.pot
src/collective/iptvusp/models/uspvideo.xml
src/collective/iptvusp/profiles/default/browserlayer.xml
src/collective/iptvusp/profiles/default/controlpanel.xml
src/collective/iptvusp/profiles/default/metadata.xml
src/collective/iptvusp/profiles/default/registry.xml
src/collective/iptvusp/profiles/default/types.xml
src/collective/iptvusp/profiles/default/types/iptvusp.uspvideo.xml
src/collective/iptvusp/profiles/uninstall/registry.xml
src/collective/iptvusp/static/video_icon.png
src/collective/iptvusp/templates/view.pt
src/collective/iptvusp/tests/__init__.py
src/collective/iptvusp/tests/test_controlpanel.py
src/collective/iptvusp/tests/test_setup.py
src/collective/iptvusp/tests/test_uspvideo.py